7san-1.0.0.dist-info/licenses/LICENSE
s7/__init__.py
s7/core.py
s7/hook.py
s7/mem.py
s7/net.py
s7/prot.py
s7/term.py
s7/val.py
7san-1.0.0.dist-info/METADATA
7san-1.0.0.dist-info/WHEEL
7san-1.0.0.dist-info/top_level.txt
7san-1.0.0.dist-info/RECORD
