Metadata-Version: 2.4
Name: 7san
Version: 1.0.0
Summary: Advanced time-based expiration and protection system for Python applications
Author: san
License: MIT
Project-URL: Homepage, https://t.me/ii00hh
Keywords: expiration,time-based,security,protection,licensing
Classifier: Development Status :: 5 - Production/Stable
Classifier: Intended Audience :: Developers
Classifier: License :: OSI Approved :: MIT License
Classifier: Programming Language :: Python :: 3
Classifier: Programming Language :: Python :: 3.7
Classifier: Programming Language :: Python :: 3.8
Classifier: Programming Language :: Python :: 3.9
Classifier: Programming Language :: Python :: 3.10
Classifier: Programming Language :: Python :: 3.11
Classifier: Programming Language :: Python :: 3.12
Classifier: Operating System :: OS Independent
Classifier: Topic :: Software Development :: Libraries :: Python Modules
Classifier: Topic :: Security
Requires-Python: >=3.7
License-File: LICENSE
Requires-Dist: psutil>=5.9.0
Requires-Dist: setuptools>=68.0.0
Dynamic: license-file
